awk.py
setup.py
awk.egg-info/PKG-INFO
awk.egg-info/SOURCES.txt
awk.egg-info/dependency_links.txt
awk.egg-info/top_level.txt