Metadata-Version: 1.1
Name: awk
Version: 1.2.1
Summary: A library to provide advanced awk-like functionalities for file manipulation in Python.
Home-page: https://github.com/SimoneBronzini/awk
Author: Simone Bronzini
Author-email: simone.bronzini@moveax.it
License: http://opensource.org/licenses/MIT
Platform: UNKNOWN
Classifier: Programming Language :: Python :: 3
Classifier: Programming Language :: Python :: 3.3
Classifier: Programming Language :: Python :: 3.4
Classifier: Programming Language :: Python :: 3.5
Classifier: Topic :: Text Processing :: General
Classifier: Topic :: Software Development :: Libraries :: Python Modules
